automl/__init__.py
automl/client/__init__.py
automl/client/core/__init__.py
automl/client/core/nativeclient/__init__.py
automl/client/core/nativeclient/_automlclientproxy.py
automl/client/core/nativeclient/_miroproxyclient.py
automl/client/core/nativeclient/_miroproxyclientv2.py
automl/client/core/nativeclient/_version.py
automl/client/core/nativeclient/abstract_nativeclient_authentication.py
automl/client/core/nativeclient/automlclassifier.py
automl/client/core/nativeclient/automlforecaster.py
automl/client/core/nativeclient/automlnativeclient.py
automl/client/core/nativeclient/automlregressor.py
automl/client/core/nativeclient/ensemble.py
automl/client/core/nativeclient/ensemble_helper.py
automl/client/core/nativeclient/nativeclient_settings.py
automl/client/core/nativeclient/py.typed
automl/client/core/nativeclient/run.py
automl/client/core/nativeclient/stack_ensemble.py
automl_client_core_nativeclient-0.0.1.0.dist-info/LICENSE.txt
automl_client_core_nativeclient-0.0.1.0.dist-info/METADATA
automl_client_core_nativeclient-0.0.1.0.dist-info/WHEEL
automl_client_core_nativeclient-0.0.1.0.dist-info/top_level.txt
automl_client_core_nativeclient-0.0.1.0.dist-info/RECORD
